afeng/__init__.py
afeng/ai/__init__.py
afeng/common/__init__.py
afeng/common/id/__init__.py
afeng/common/id/code_generator.py
afeng/common/id/id_code_tools.py
afeng/common/id/uuid_tools.py
afeng/common/log/__init__.py
afeng/db/__init__.py
afeng/db/common/__init__.py
afeng/db/common/schemas/__init__.py
afeng/db/common/schemas/page_schemas.py
afeng/db/common/tools/__init__.py
afeng/db/common/tools/db_type_tools.py
afeng/db/sqlalchemy/__init__.py
afeng/db/sqlalchemy/base.py
afeng/db/sqlalchemy/base_models.py
afeng/db/sqlalchemy/crud_tools.py
afeng/plugin/__init__.py
afeng/plugin/core/__init__.py
afeng/plugin/email/__init__.py
afeng/plugin/email/metadata.json
afeng/plugin/user/__init__.py
afeng/plugin/user/metadata.json
afeng/plugin/user/models/__init__.py
afeng/plugin/user/models/base_user.py
afeng/plugin/user/README.md
afeng/plugin/user/requirements.txt
afeng_tools-0.0.1.1.dist-info/licenses/LICENSE.txt
afeng_tools-0.0.1.1.dist-info/METADATA
afeng_tools-0.0.1.1.dist-info/WHEEL
afeng_tools-0.0.1.1.dist-info/RECORD
