Metadata-Version: 2.4
Name: afeng-tools
Version: 0.0.1.1
Summary: 阿锋的工具箱
License: GPLv3
License-File: LICENSE.txt
Author: 陈铁锋
Author-email: imchentiefeng@aliyun.com
Requires-Python: >=3.10
Classifier: Programming Language :: Python :: 3
Classifier: Operating System :: OS Independent
Project-URL: Homepage, https://gitee.com/python-playing/afeng-tools
Project-URL: Issues, https://gitee.com/python-playing/afeng-tools/issues
